ninjag/__init__.py
ninjag/check_input.py
ninjag/cli.py
ninjag/main.py
ninjag/show_usage.py
ninjag/usage.txt
ninjag/core/__init__.py
ninjag/core/ninja_build.py
ninjag/core/ninja_build_dep.py
ninjag/core/ninja_build_pipe.py
ninjag/core/ninja_const.py
ninjag/core/ninja_def.py
ninjag/core/ninja_generate.py
ninjag/core/ninja_io.py
ninjag/core/ninja_key_value_pairs.py
ninjag/core/ninja_phony.py
ninjag/core/ninja_rule.py
ninjag/io/__init__.py
ninjag/io/read/__init__.py
ninjag/io/read/assert_any.py
ninjag/io/read/check_definitions.py
ninjag/io/read/check_input.py
ninjag/io/read/check_tasks.py
ninjag/io/read/check_types.py
ninjag/io/read/default_config.py
ninjag/io/read/read_config_files.py
ninjag/tk/__init__.py
ninjag/tk/dictTK/__init__.py
ninjag/tk/dictTK/merge.py
ninjag/tk/dictTK/merge2.py
ninjag/tk/fnTK/__init__.py
ninjag/tk/fnTK/compose.py
ninjag/tk/fnTK/compose2.py
ninjag/tk/fnTK/reduce.py
ninjag/tk/ioTK/__init__.py
ninjag/tk/ioTK/read_all.py
ninjag/tk/ioTK/save_text.py
ninjag-0.3.6.dist-info/DESCRIPTION.rst
ninjag-0.3.6.dist-info/METADATA
ninjag-0.3.6.dist-info/RECORD
ninjag-0.3.6.dist-info/WHEEL
ninjag-0.3.6.dist-info/entry_points.txt
ninjag-0.3.6.dist-info/metadata.json
ninjag-0.3.6.dist-info/top_level.txt
