Metadata-Version: 2.0
Name: ninjag
Version: 0.3.6
Summary: Ninja config file generator
Home-page: https://github.com/yuhangwang/ninjag-python
Author: Steven(Yuhang) Wang
Author-email: UNKNOWN
License: MIT
Requires-Dist: PyYAML
Requires-Dist: typing
Provides-Extra: test
Requires-Dist: pytest; extra == 'test'
